setup.py
unittestone.py
UnittestOne.egg-info/PKG-INFO
UnittestOne.egg-info/SOURCES.txt
UnittestOne.egg-info/dependency_links.txt
UnittestOne.egg-info/requires.txt
UnittestOne.egg-info/top_level.txt
test/test_new_asserts.py
test/test_old_asserts.py