Metadata-Version: 1.0
Name: UnittestOne
Version: 0.1
Summary: An Assertion Framework for API testing
Home-page: https://github.com/klrmn/Unittest-One
Author: Leah Klearman
Author-email: lklrmn at gmail dot com
License: UNKNOWN
Platform: UNKNOWN
Classifier: Development Status :: 3 - Alpha
Classifier: Intended Audience :: Developers
Classifier: License :: OSI Approved :: The MIT License (MIT)
Classifier: Operating System :: POSIX
Classifier: Operating System :: Microsoft :: Windows
Classifier: Operating System :: MacOS :: MacOS X
Classifier: Topic :: Software Development :: Testing
Classifier: Topic :: Software Development :: Libraries
Classifier: Programming Language :: Python
